{"elapsed":"2.741","endpoint-url":"https://dservices2.arcgis.com/LrUbY6lLLgV3tEa5/arcgis/services/Article_4_Directions_View_WFS/WFSServer?service=wfs&request=GetFeature&TypeNames=Article_4&OutputFormat=GML2","entry-date":"2023-11-02T00:16:06.917221","request-headers":{"Accept":"*/*","Accept-Encoding":"gzip, deflate","Connection":"keep-alive","User-Agent":"DLUHC Digital Land"},"resource":"8dba40bd6686c37f00cf7c9844c63404f26e237e049252b4f98f089eae7e1764","response-headers":{"Connection":"keep-alive","Content-Length":"414746","Content-Type":"application/xml;charset=UTF-8","Date":"Thu, 02 Nov 2023 00:17:00 GMT","Server":"Microsoft-IIS/10.0","Vary":"Origin","X-ArcGIS-InstanceID":"4QAQOXHRC000000","X-Powered-By":"ASP.NET","X-XSS-Protection":"1; mode=block"},"ssl-verify":true,"status":"200"}