{"elapsed":"0.657","endpoint-url":"https://maps.buckscc.gov.uk/arcgis/services/PLANNING/A4D_AV/MapServer/WFSServer?request=GetFeature&service=WFS&typename=PLANNING_A4D_AV:Article_4_Direction_s__Aylesbury_Vale_","entry-date":"2022-04-28T16:59:11.043077","request-headers":{"Accept":"*/*","Accept-Encoding":"gzip, deflate","Connection":"keep-alive","User-Agent":"DLUHC Digital Land"},"resource":"cbb306778db2c6ffa1d7770bf0df2635cd4bcc905fc60843651d27fb442edb8b","response-headers":{"Content-Type":"application/xml;charset=UTF-8","Date":"Thu, 28 Apr 2022 16:59:11 GMT","Keep-Alive":"timeout=60","Server":"","Transfer-Encoding":"chunked, chunked","X-Content-Type-Options":"nosniff","X-XSS-Protection":"1; mode=block","accept":"text/html, image/gif, image/jpeg, *; q=.2, */*; q=.2","cache-control":"no-cache","connection":"keep-alive, keep-alive","host":"maps.buckscc.gov.uk","pragma":"no-cache","referer":"6628c0c3-d1a8-4842-9cad-43f16baeb999","referrer":"6628c0c3-d1a8-4842-9cad-43f16baeb999","response_buffer_size":"8192","response_character_encoding":"UTF-8","response_content_type":"application/xml","user-agent":"Java/11.0.6"},"ssl-verify":true,"status":"200"}