{"elapsed":"0.1","endpoint-url":"https://raw.githubusercontent.com/digital-land/article-4-direction-collection/main/data/Southwark/Article%204%20_%20HMO%20Henshaw%20Street.gpkg","entry-date":"2023-02-23T00:18:08.902123","request-headers":{"Accept":"*/*","Accept-Encoding":"gzip, deflate","Connection":"keep-alive","User-Agent":"DLUHC Digital Land"},"resource":"9510b41e61d9af455792dc1b4eb80d7600671804b9e8788de32c61b1ce2435d1","response-headers":{"Accept-Ranges":"bytes","Access-Control-Allow-Origin":"*","Cache-Control":"max-age=300","Connection":"keep-alive","Content-Length":"90112","Content-Security-Policy":"default-src 'none'; style-src 'unsafe-inline'; sandbox","Content-Type":"application/octet-stream","Date":"Thu, 23 Feb 2023 00:18:12 GMT","ETag":"W/\"18008a2ed2a5d2d5548df01c4462567af40d6b12e547153c0c06b96b24841fd3\"","Expires":"Thu, 23 Feb 2023 00:23:12 GMT","Source-Age":"0","Strict-Transport-Security":"max-age=31536000","Vary":"Authorization,Accept-Encoding,Origin","Via":"1.1 varnish","X-Cache":"MISS","X-Cache-Hits":"0","X-Content-Type-Options":"nosniff","X-Fastly-Request-ID":"bba1f256cb9768ebc0a9b8a353b8e802b0c43ac4","X-Frame-Options":"deny","X-GitHub-Request-Id":"8074:4964:2DC542:42AE50:63F6B0C4","X-Served-By":"cache-iad-kiad7000061-IAD","X-Timer":"S1677111492.214419,VS0,VE88","X-XSS-Protection":"1; mode=block"},"ssl-verify":true,"status":"200"}