{"elapsed":"2.419","endpoint-url":"https://maps.buckscc.gov.uk/arcgis/services/PLANNING/A4D_WDC/MapServer/WFSServer?request=GetFeature&service=WFS&typename=PLANNING_A4D_WDC:Article_4_Direction_s__Wycombe_","entry-date":"2023-02-24T00:17:13.554707","request-headers":{"Accept":"*/*","Accept-Encoding":"gzip, deflate","Connection":"keep-alive","User-Agent":"DLUHC Digital Land"},"resource":"095bdd47789156b238b11efb62b2d8500ca48f0a934a6204cf840a706e6bbee4","response-headers":{"Content-Type":"application/xml;charset=UTF-8","Date":"Fri, 24 Feb 2023 00:17:20 GMT","Keep-Alive":"timeout=60","Server":"","Transfer-Encoding":"chunked, chunked","X-Content-Type-Options":"nosniff","X-XSS-Protection":"1; mode=block","accept":"text/html, image/gif, image/jpeg, *; q=.2, */*; q=.2","cache-control":"no-cache","connection":"keep-alive, keep-alive","host":"maps.buckscc.gov.uk","pragma":"no-cache","referer":"cc0dbfd0-ad49-477a-99ea-b9ed24aeae33","referrer":"cc0dbfd0-ad49-477a-99ea-b9ed24aeae33","response_buffer_size":"8192","response_character_encoding":"UTF-8","response_content_type":"application/xml","response_status_code":"200","user-agent":"Java/11.0.6"},"ssl-verify":true,"status":"200"}