{"elapsed":"3.611","endpoint-url":"https://maps.buckscc.gov.uk/arcgis/services/PLANNING/A4D_WDC/MapServer/WFSServer?request=GetFeature&service=WFS&typename=PLANNING_A4D_WDC:Article_4_Direction_s__Wycombe_","entry-date":"2023-01-26T00:17:52.640619","request-headers":{"Accept":"*/*","Accept-Encoding":"gzip, deflate","Connection":"keep-alive","User-Agent":"DLUHC Digital Land"},"resource":"0b519a0edfbedc1a8e31cd91a607737a058c66e8486715371930af34fe29e6ec","response-headers":{"Content-Type":"application/xml;charset=UTF-8","Date":"Thu, 26 Jan 2023 00:18:04 GMT","Keep-Alive":"timeout=60","Server":"","Transfer-Encoding":"chunked, chunked","X-Content-Type-Options":"nosniff","X-XSS-Protection":"1; mode=block","accept":"text/html, image/gif, image/jpeg, *; q=.2, */*; q=.2","cache-control":"no-cache","connection":"keep-alive, keep-alive","host":"maps.buckscc.gov.uk","pragma":"no-cache","referer":"32bd36ec-d81c-459a-bb09-d94d2ae82e0e","referrer":"32bd36ec-d81c-459a-bb09-d94d2ae82e0e","response_buffer_size":"8192","response_character_encoding":"UTF-8","response_content_type":"application/xml","response_status_code":"200","user-agent":"Java/11.0.6"},"ssl-verify":true,"status":"200"}