{"elapsed":"0.212","endpoint-url":"https://raw.githubusercontent.com/digital-land/article-4-direction-collection/main/data/Southwark/Article%204%20_%20Demolition%20of%20the%20Stables%20and%20the%20Forge%20on%20Catlin%20Street.gpkg","entry-date":"2023-11-14T00:16:37.960398","request-headers":{"Accept":"*/*","Accept-Encoding":"gzip, deflate","Connection":"keep-alive","User-Agent":"DLUHC Digital Land"},"resource":"c70e657dab5368c1ba6514000182e571c46de6f483f14e38a272b636901c250d","response-headers":{"Accept-Ranges":"bytes","Access-Control-Allow-Origin":"*","Cache-Control":"max-age=300","Connection":"keep-alive","Content-Length":"94208","Content-Security-Policy":"default-src 'none'; style-src 'unsafe-inline'; sandbox","Content-Type":"application/octet-stream","Cross-Origin-Resource-Policy":"cross-origin","Date":"Tue, 14 Nov 2023 00:16:42 GMT","ETag":"W/\"4fafb5eb56cb1a8ad816650a3b6c33be243a06851f41f3ce998d998ea1b5e8c9\"","Expires":"Tue, 14 Nov 2023 00:21:42 GMT","Source-Age":"0","Strict-Transport-Security":"max-age=31536000","Vary":"Authorization,Accept-Encoding,Origin","Via":"1.1 varnish","X-Cache":"MISS","X-Cache-Hits":"0","X-Content-Type-Options":"nosniff","X-Fastly-Request-ID":"7ddb1ab26f189c77f73004d737ef04210a2a2cf0","X-Frame-Options":"deny","X-GitHub-Request-Id":"2FE4:01E9:13E6D2:191650:6552BC69","X-Served-By":"cache-bur-kbur8200159-BUR","X-Timer":"S1699921002.102519,VS0,VE196","X-XSS-Protection":"1; mode=block"},"ssl-verify":true,"status":"200"}