{"elapsed":"0.12","endpoint-url":"https://raw.githubusercontent.com/digital-land/article-4-direction-collection/main/data/article-4-directions.csv","entry-date":"2021-06-01T01:17:32.908238","request-headers":{"Accept":"*/*","Accept-Encoding":"gzip, deflate","Connection":"keep-alive","User-Agent":"Digital Land"},"resource":"223b31dab8f2af16bd637db4be4e17239a7405a5f585200610c05cd64440c988","response-headers":{"Accept-Ranges":"bytes","Access-Control-Allow-Origin":"*","Cache-Control":"max-age=300","Connection":"keep-alive","Content-Encoding":"gzip","Content-Length":"1387","Content-Security-Policy":"default-src 'none'; style-src 'unsafe-inline'; sandbox","Content-Type":"text/plain; charset=utf-8","Date":"Tue, 01 Jun 2021 01:17:33 GMT","ETag":"W/\"f3dd76e811b97f1a922e20090ec21db429adbe613c81aaf904160125b268fb09\"","Expires":"Tue, 01 Jun 2021 01:22:33 GMT","Source-Age":"0","Strict-Transport-Security":"max-age=31536000","Vary":"Authorization,Accept-Encoding","Via":"1.1 varnish","X-Cache":"MISS","X-Cache-Hits":"0","X-Content-Type-Options":"nosniff","X-Fastly-Request-ID":"cc076a1aff1bbb504eae93070d25bbe851daa34a","X-Frame-Options":"deny","X-GitHub-Request-Id":"EB72:41DE:4776E0:72E1A8:60B58AAD","X-Served-By":"cache-bwi5028-BWI","X-Timer":"S1622510253.376503,VS0,VE86","X-XSS-Protection":"1; mode=block"},"ssl-verify":true,"status":"200"}